ipycanvas_drawing/__init__.py
ipycanvas_drawing/drawing_widget.py
ipycanvas_drawing-0.0.5.dist-info/METADATA
ipycanvas_drawing-0.0.5.dist-info/WHEEL
ipycanvas_drawing-0.0.5.dist-info/licenses/LICENSE
ipycanvas_drawing-0.0.5.dist-info/RECORD
