Metadata-Version: 2.1
Name: ipycanvas_drawing
Version: 0.0.5
Summary: A small widget to let users draw by hand in a Jupyter notebook.
Project-URL: Homepage, https://github.com/rubenwiersma/ipycanvas_drawing
Project-URL: Bug Tracker, https://github.com/rubenwiersma/ipycanvas_drawing/issues
Author-email: Ruben Wiersma <rubenwiersma@gmail.com>
License-File: LICENSE
Requires-Python: >3.6
Requires-Dist: ipycanvas
Requires-Dist: ipywidgets
Requires-Dist: numpy
